ssrspeed/__init__.py
ssrspeed/__main__.py
ssrspeed/config/__init__.py
ssrspeed/config/config.py
ssrspeed/core/__init__.py
ssrspeed/core/core.py
ssrspeed/download/__init__.py
ssrspeed/download/download.py
ssrspeed/launcher/__init__.py
ssrspeed/launcher/base.py
ssrspeed/launcher/hysteria.py
ssrspeed/launcher/shadowsocks.py
ssrspeed/launcher/shadowsocksr.py
ssrspeed/launcher/trojan.py
ssrspeed/launcher/v2ray.py
ssrspeed/launcher/xray.py
ssrspeed/parser/__init__.py
ssrspeed/parser/parser.py
ssrspeed/parser/bottom/__init__.py
ssrspeed/parser/bottom/bottom.py
ssrspeed/parser/clash/__init__.py
ssrspeed/parser/clash/cparser.py
ssrspeed/parser/conf/__init__.py
ssrspeed/parser/conf/hyc.py
ssrspeed/parser/conf/ssc.py
ssrspeed/parser/conf/trojanc.py
ssrspeed/parser/conf/v2rayc.py
ssrspeed/parser/filter/__init__.py
ssrspeed/parser/filter/filter.py
ssrspeed/parser/hy/__init__.py
ssrspeed/parser/hy/hparser.py
ssrspeed/parser/ss/__init__.py
ssrspeed/parser/ss/basic.py
ssrspeed/parser/ss/sclash.py
ssrspeed/parser/ss/sip002.py
ssrspeed/parser/ss/sparser.py
ssrspeed/parser/ss/ssd.py
ssrspeed/parser/ssr/__init__.py
ssrspeed/parser/ssr/primary.py
ssrspeed/parser/ssr/rparser.py
ssrspeed/parser/trojan/__init__.py
ssrspeed/parser/trojan/tparser.py
ssrspeed/parser/v2ray/__init__.py
ssrspeed/parser/v2ray/quantumult.py
ssrspeed/parser/v2ray/vclash.py
ssrspeed/parser/v2ray/vless.py
ssrspeed/parser/v2ray/vmess.py
ssrspeed/parser/v2ray/vparser.py
ssrspeed/path/__init__.py
ssrspeed/path/path.py
ssrspeed/resource/ssrspeed.example.json
ssrspeed/resource/static/custom/readme.md
ssrspeed/resource/static/fonts/LXGWBright-Medium.otf
ssrspeed/resource/static/fonts/SourceHanSansCN-Medium.otf
ssrspeed/resource/static/logos/Abema.png
ssrspeed/resource/static/logos/Bahamut.png
ssrspeed/resource/static/logos/Bilibili.png
ssrspeed/resource/static/logos/Dazn.png
ssrspeed/resource/static/logos/DisneyPlus.png
ssrspeed/resource/static/logos/HBO.png
ssrspeed/resource/static/logos/Netflix.png
ssrspeed-1.5.2.dist-info/LICENSE
ssrspeed-1.5.2.dist-info/METADATA
ssrspeed-1.5.2.dist-info/WHEEL
ssrspeed-1.5.2.dist-info/entry_points.txt
ssrspeed-1.5.2.dist-info/top_level.txt
ssrspeed-1.5.2.dist-info/RECORD
