Metadata-Version: 2.1
Name: ssrspeed
Version: 1.5.2
Summary: A simple tool to test nodes.
Home-page: https://github.com/OreosLab/SSRSpeedN
License: GPL-3.0 License
Keywords: ssr,speed,test
Classifier: Development Status :: 4 - Beta
Classifier: License :: OSI Approved :: GNU General Public License v3 (GPLv3)
Classifier: Programming Language :: Python
Classifier: Programming Language :: Python :: 3
Classifier: Programming Language :: Python :: 3.8
Classifier: Programming Language :: Python :: 3.9
Classifier: Programming Language :: Python :: 3.10
Classifier: Programming Language :: Python :: 3 :: Only
Classifier: Programming Language :: Python :: Implementation :: CPython
Requires-Python: >=3.8.0
License-File: LICENSE
Requires-Dist: aiofiles
Requires-Dist: aiohttp-socks
Requires-Dist: Flask-Cors
Requires-Dist: geoip2
Requires-Dist: loguru
Requires-Dist: pilmoji
Requires-Dist: PySocks
Requires-Dist: PyYAML
Requires-Dist: requests
Requires-Dist: selenium (==4.4.3)
Requires-Dist: tqdm
Requires-Dist: webdriver-manager
